{"feishu-wiki_docs_首页_首页下的文档_二级文档_三级文档_四级文档.md":"7cq1XG2F","yuque_gvnxobqogetukays.md":"p2N_352e","yuque_la9toqncox96kfp8.md":"ZQqfo14r","yuque-pwd_te7ash7ybckgi60w.md":"--xToIhN","yuque_notion-example.md":"EiGfptWL","yuque-pwd_la9toqncox96kfp8.md":"yz6yKtZz","yuque_raqyleng501h23p1.md":"8UHHFKAI","feishu_一级子文件夹_iyyzdn2azoiwosxihracjp18ntb.md":"k-b6x-kN","yuque_start.md":"HRR0Ceal","yuque_notion-markdown.md":"pUAERsVd","notion_flowus-markdown.md":"a3IoJ4L_","yuque_te7ash7ybckgi60w.md":"ru97KZZC","yuque_ubcut43kgf97fag6.md":"9e9bJar6","yuque_xe160pqsumi6bqnz.md":"KESz7L5R","yuque_vy55q9xwlqlsfrvk.md":"746TFQHr","notion_gvnxobqogetukays.md":"WwBzvhLH","feishu_vulcdslgxotcb1xli1bcwwdpnva.md":"i__b-j4W","notion_cq6p8hxizn1ogwgm.md":"WA-hnRZ-","notion_blogpal.md":"dEPVCHmJ","yuque-pwd_zuzvbv2lqhvllgit.md":"IVEzPgms","notion_deploy-platform.md":"ambfbUwN","yuque-pwd_gvnxobqogetukays.md":"YhfSrCMx","notion_xe160pqsumi6bqnz.md":"9nOZGzBl","notion_bry3d3lwe206xuor.md":"GL7abJzd","notion_yuque-markdown.md":"McPkHtcZ","notion_notion-example.md":"wjq3Gmar","yuque-pwd_introduce.md":"4LStsVdn","yuque-pwd_vy55q9xwlqlsfrvk.md":"gMzgPwp4","notion_local-test.md":"Igz9VOHq","notion_image-platform.md":"hukfmRpz","yuque-pwd_ubcut43kgf97fag6.md":"ABGQnT9v","yuque-pwd_yuque-example.md":"XMoijKLx","notion_write-platform.md":"6gKXqeyT","yuque-pwd_yuque-markdown.md":"1jdDkqD2","yuque-pwd_raqyleng501h23p1.md":"2mYPPzRE","notion_flowus-example.md":"MZivRBjg","yuque_cq6p8hxizn1ogwgm.md":"VRDhV57K","notion_la9toqncox96kfp8.md":"paMtmBP-","yuque-pwd_start.md":"V9bSRVhk","yuque_yuque-example.md":"uKFYzhZo","flowus_flowus-example-2.md":"TUqfTaQA","feishu-wiki_docs_测试.md":"m8DvM1oc","yuque-pwd_bry3d3lwe206xuor.md":"Ol3MHsXm","notion_ubcut43kgf97fag6.md":"2Bwt8BBC","notion_zuzvbv2lqhvllgit.md":"uGc8VOUZ","notion_notion-markdown.md":"DZPxt0Jw","yuque-pwd_notion-example.md":"512oJIXZ","yuque-pwd_cq6p8hxizn1ogwgm.md":"TKGEN2_D","yuque_bry3d3lwe206xuor.md":"EaXeSx-L","notion_config-catalog.md":"eWg434nB","yuque-pwd_notion-markdown.md":"uF4yZ8q0","index.md":"rzu9dIEQ","yuque_introduce.md":"DzW7aUYC","notion_introduce.md":"iK-ipYFM","notion_feishu-example.md":"RuVnakPK","feishu_一级子文件夹_二级文件夹_fpdsdgyc4ofs56xteghcnx2invf.md":"kMgytuBb","yuque-pwd_fe8ywmt999gon12w.md":"vLivcg7a","flowus_flowus-example.md":"geBTX9tY","yuque_yuque-markdown.md":"gnl5hcmk","yuque_zuzvbv2lqhvllgit.md":"-BgrXUVc","notion_yuque-example.md":"53aSFJSO","yuque_fe8ywmt999gon12w.md":"GefFPcy0","notion_qa.md":"FYGOOevu","notion_vy55q9xwlqlsfrvk.md":"dc_vOjiG","notion_start.md":"6P3Y9lBK","yuque-pwd_xe160pqsumi6bqnz.md":"LNcZbuIR","notion_raqyleng501h23p1.md":"VuuHdR0N","notion_fe8ywmt999gon12w.md":"gECAUJ1e"}
