{"feishu_vulcdslgxotcb1xli1bcwwdpnva.md":"Ga2P05Uf","notion_bry3d3lwe206xuor.md":"m2YMBo0Q","notion_introduce.md":"7KHAZv2R","notion_cq6p8hxizn1ogwgm.md":"Rfp3JUyi","notion_deploy-platform.md":"XUylW2Ux","notion_config-catalog.md":"nkVo0Xxy","notion_la9toqncox96kfp8.md":"ydnfwlY9","yuque-pwd_introduce.md":"z_HK8OWE","yuque-pwd_start.md":"TmaOqPBg","yuque-pwd_ubcut43kgf97fag6.md":"Ac757-nB","yuque-pwd_yuque-markdown.md":"WQbJMoa_","notion_fe8ywmt999gon12w.md":"vFA4MPVk","yuque-pwd_vy55q9xwlqlsfrvk.md":"S2QKKN14","yuque-pwd_xe160pqsumi6bqnz.md":"Ahs08KHv","yuque_cq6p8hxizn1ogwgm.md":"sWxD7mrY","yuque_introduce.md":"A27n9FAs","yuque_la9toqncox96kfp8.md":"XfYl8ViJ","yuque_gvnxobqogetukays.md":"6jpA8j52","yuque_notion-example.md":"afq0C94R","yuque_raqyleng501h23p1.md":"gBoeXjGU","yuque_notion-markdown.md":"sMKFk1C-","yuque_te7ash7ybckgi60w.md":"-45q5tGK","yuque_start.md":"XZmo-FfE","yuque_ubcut43kgf97fag6.md":"WstcRPgf","yuque_fe8ywmt999gon12w.md":"VS40WgBl","yuque_yuque-example.md":"DazLcK59","yuque_yuque-markdown.md":"kBE9XSCx","yuque_vy55q9xwlqlsfrvk.md":"rUgJ8r9-","yuque_xe160pqsumi6bqnz.md":"FQ5ZiF5B","notion_start.md":"TYlGO1FG","notion_yuque-example.md":"wEdfSq6v","notion_yuque-markdown.md":"XsDw2w3I","yuque-pwd_bry3d3lwe206xuor.md":"IMAp-hhT","feishu-wiki_docs_测试.md":"i03pfV1S","notion_zuzvbv2lqhvllgit.md":"5aa_kqJB","feishu_一级子文件夹_iyyzdn2azoiwosxihracjp18ntb.md":"Gw0TRDb6","notion_local-test.md":"9wfoIVtm","notion_notion-markdown.md":"yaRoNGrO","feishu-wiki_docs_首页_首页下的文档_二级文档_三级文档_四级文档.md":"uQwl_gp8","feishu_一级子文件夹_二级文件夹_fpdsdgyc4ofs56xteghcnx2invf.md":"DCgcuAwX","notion_notion-example.md":"uRZ95ykB","flowus_flowus-example-2.md":"5phlrrTT","index.md":"F5KEwyVF","notion_qa.md":"IOWARatI","flowus_flowus-example.md":"lJfi7gHU","notion_blogpal.md":"KSS71z46","notion_flowus-example.md":"MgY1EO_Q","notion_feishu-example.md":"0K4PGSHh","yuque-pwd_cq6p8hxizn1ogwgm.md":"pbYUlp3h","notion_raqyleng501h23p1.md":"QtJldMvD","notion_write-platform.md":"ClCopr2J","notion_ubcut43kgf97fag6.md":"pZ0xy2Vh","yuque-pwd_notion-example.md":"q9NAkP96","yuque-pwd_te7ash7ybckgi60w.md":"RrK3_TWl","yuque-pwd_notion-markdown.md":"RBCesg9X","yuque-pwd_gvnxobqogetukays.md":"xwwFvgMu","yuque-pwd_raqyleng501h23p1.md":"pGMSJFi2","notion_flowus-markdown.md":"LQPY6ANI","notion_vy55q9xwlqlsfrvk.md":"Lyc7qxTv","notion_gvnxobqogetukays.md":"fRbRJS6b","notion_image-platform.md":"1AEDp4wC","yuque_bry3d3lwe206xuor.md":"aQpGekhI","notion_xe160pqsumi6bqnz.md":"apxrFLNg","yuque-pwd_zuzvbv2lqhvllgit.md":"kHRwC-R8","yuque-pwd_la9toqncox96kfp8.md":"EItcUdal","yuque-pwd_fe8ywmt999gon12w.md":"5UTawlrw","yuque-pwd_yuque-example.md":"7QKFA4Zn","yuque_zuzvbv2lqhvllgit.md":"OXLI9y7C"}
