{"notion_cq6p8hxizn1ogwgm.md":"5517cf41","notion_flowus-markdown.md":"74e8e2a2","notion_gvnxobqogetukays.md":"4e9d25a4","notion_introduce.md":"b97ef266","notion_la9toqncox96kfp8.md":"ed1daafd","notion_notion-example.md":"9d3007c2","notion_notion-markdown.md":"41393433","notion_raqyleng501h23p1.md":"1aef22f4","notion_start.md":"fad8f55f","notion_te7ash7ybckgi60w.md":"6bd96bf9","notion_ubcut43kgf97fag6.md":"f9e107ac","notion_vy55q9xwlqlsfrvk.md":"8f85915f","notion_xe160pqsumi6bqnz.md":"5d70690b","notion_flowus-example.md":"e1029dec","notion_yuque-example.md":"f350b68c","yuque-pwd_bry3d3lwe206xuor.md":"279d293e","notion_yuque-markdown.md":"881f5b59","notion_zuzvbv2lqhvllgit.md":"28b17a6d","yuque-pwd_cq6p8hxizn1ogwgm.md":"5e5af33b","yuque-pwd_gvnxobqogetukays.md":"ede852b9","notion_fe8ywmt999gon12w.md":"734f9ad1","yuque-pwd_la9toqncox96kfp8.md":"b1bee572","yuque-pwd_notion-example.md":"98a993e5","yuque-pwd_introduce.md":"1acc3f46","index.md":"d32dbd97","notion_bry3d3lwe206xuor.md":"686518e1","yuque_la9toqncox96kfp8.md":"acdacbf0","yuque_notion-example.md":"9ce326f9","yuque_raqyleng501h23p1.md":"39ff7d0d","yuque_start.md":"7a9abfb6","yuque_ubcut43kgf97fag6.md":"e929027a","flowus_flowus-example.md":"5dfdbf3e","yuque_vy55q9xwlqlsfrvk.md":"af374a96","yuque_te7ash7ybckgi60w.md":"7bbf4038","yuque_zuzvbv2lqhvllgit.md":"46877c14","yuque-pwd_raqyleng501h23p1.md":"be1558e4","yuque-pwd_start.md":"e8a6c61d","yuque_notion-markdown.md":"5e9d3be2","yuque_yuque-markdown.md":"0cdb4310","yuque-pwd_te7ash7ybckgi60w.md":"8d496629","yuque_xe160pqsumi6bqnz.md":"34ffec8a","yuque_yuque-example.md":"2c2a7a22","yuque-pwd_notion-markdown.md":"8672ab58","yuque-pwd_ubcut43kgf97fag6.md":"aa3d6c6c","yuque-pwd_vy55q9xwlqlsfrvk.md":"fc9fd23a","yuque-pwd_xe160pqsumi6bqnz.md":"b1224351","yuque-pwd_yuque-example.md":"65bf054b","yuque-pwd_yuque-markdown.md":"77af7038","yuque-pwd_zuzvbv2lqhvllgit.md":"b171c44c","yuque_introduce.md":"966743e3","yuque_fe8ywmt999gon12w.md":"51b79be9","yuque_gvnxobqogetukays.md":"32b55af9","yuque_bry3d3lwe206xuor.md":"5bb3ec2d","yuque-pwd_fe8ywmt999gon12w.md":"aa84b8d0","yuque_cq6p8hxizn1ogwgm.md":"899e411a"}
