{"yuque_notion-example.md":"aa36c35d","yuque_la9toqncox96kfp8.md":"8bc7fe9d","yuque_gvnxobqogetukays.md":"96a463d9","feishu_一级子文件夹_二级文件夹_fpdsdgyc4ofs56xteghcnx2invf.md":"fc7c96b7","flowus_flowus-example-2.md":"aefaac0b","feishu_一级子文件夹_iyyzdn2azoiwosxihracjp18ntb.md":"05164b16","index.md":"4951dc89","flowus_flowus-example.md":"a9eb595e","notion_bry3d3lwe206xuor.md":"cf291ef9","notion_cq6p8hxizn1ogwgm.md":"1625d3c8","notion_config-catalog.md":"651d2e3f","notion_flowus-example.md":"ffa9ab0f","notion_gvnxobqogetukays.md":"05ccd9a0","notion_feishu-example.md":"7d81427b","notion_flowus-markdown.md":"64f9efd4","notion_notion-markdown.md":"ce66e3b6","notion_raqyleng501h23p1.md":"22458486","notion_qa.md":"e99cb6e6","notion_start.md":"30445600","notion_local-test.md":"31128e11","notion_ubcut43kgf97fag6.md":"cf2bc867","notion_write-platform.md":"54d37481","notion_xe160pqsumi6bqnz.md":"4caa33a7","notion_vy55q9xwlqlsfrvk.md":"4b39ed22","notion_yuque-example.md":"85548120","yuque-pwd_bry3d3lwe206xuor.md":"cd4e6e2a","notion_yuque-markdown.md":"026d15c0","notion_zuzvbv2lqhvllgit.md":"c039be4a","yuque-pwd_cq6p8hxizn1ogwgm.md":"e1f5dbd9","yuque-pwd_introduce.md":"14c1e92d","yuque-pwd_la9toqncox96kfp8.md":"2471f4fa","yuque-pwd_notion-example.md":"01224382","yuque-pwd_gvnxobqogetukays.md":"8fdc3f4e","yuque-pwd_raqyleng501h23p1.md":"2f6adab2","yuque-pwd_fe8ywmt999gon12w.md":"1e9af019","yuque-pwd_notion-markdown.md":"d3c53797","yuque-pwd_te7ash7ybckgi60w.md":"7848429f","yuque-pwd_ubcut43kgf97fag6.md":"7d7a4621","yuque-pwd_xe160pqsumi6bqnz.md":"6d3e3387","yuque-pwd_yuque-markdown.md":"65eda074","yuque-pwd_zuzvbv2lqhvllgit.md":"9b3a2b77","yuque-pwd_yuque-example.md":"08368f0b","yuque_bry3d3lwe206xuor.md":"002e3ee8","yuque-pwd_vy55q9xwlqlsfrvk.md":"d2e7d3eb","yuque_cq6p8hxizn1ogwgm.md":"cd50e66e","yuque_introduce.md":"04847a58","yuque_fe8ywmt999gon12w.md":"7a3fae4b","yuque_notion-markdown.md":"dd1f9ad1","yuque_raqyleng501h23p1.md":"4b8317f8","yuque_start.md":"b0532b90","yuque_te7ash7ybckgi60w.md":"afa8b315","yuque_ubcut43kgf97fag6.md":"b635c42e","yuque_vy55q9xwlqlsfrvk.md":"b65915bf","yuque_yuque-example.md":"58bc8443","yuque_yuque-markdown.md":"0ad9f042","yuque_zuzvbv2lqhvllgit.md":"8892b6d1","yuque_xe160pqsumi6bqnz.md":"7409fd2d","notion_image-platform.md":"6ccca1ea","feishu-wiki_docs_首页_首页下的文档_二级文档_三级文档_四级文档.md":"6a005877","feishu_vulcdslgxotcb1xli1bcwwdpnva.md":"b3657aa1","feishu-wiki_docs_测试.md":"bd2a8348","notion_deploy-platform.md":"8c5b2747","notion_fe8ywmt999gon12w.md":"bc47921b","notion_la9toqncox96kfp8.md":"233432f4","notion_introduce.md":"6c720523","yuque-pwd_start.md":"8a363673","notion_notion-example.md":"5f42f685"}
