{"feishu_一级文件夹下的文档_iyyzdn2azoiwosxihracjp18ntb.md":"2c8f742e","notion_image-platform.md":"375aa6ce","flowus_flowus-example.md":"116ffffe","index.md":"a66407ca","notion_bry3d3lwe206xuor.md":"637679df","notion_deploy-platform.md":"ae337252","notion_fe8ywmt999gon12w.md":"74b13a87","notion_feishu-example.md":"1b9dca1c","notion_flowus-example.md":"3ca2bd8b","notion_flowus-markdown.md":"bfbc8292","notion_gvnxobqogetukays.md":"4196e5c0","notion_cq6p8hxizn1ogwgm.md":"8370f8a1","notion_config-catalog.md":"1b8571cf","notion_notion-example.md":"3611f713","notion_introduce.md":"3d91bf26","notion_notion-markdown.md":"ddd01b23","notion_local-test.md":"d7dd845f","notion_la9toqncox96kfp8.md":"55e999bd","yuque-pwd_yuque-markdown.md":"f6d0dc2b","yuque-pwd_yuque-example.md":"123822ad","yuque-pwd_zuzvbv2lqhvllgit.md":"e4a4d735","yuque_bry3d3lwe206xuor.md":"98155d21","yuque_la9toqncox96kfp8.md":"b4fada13","yuque_notion-example.md":"2cd5180e","yuque_notion-markdown.md":"ab1ae7b6","yuque_raqyleng501h23p1.md":"c0e2ea24","yuque-pwd_xe160pqsumi6bqnz.md":"8c073135","yuque_te7ash7ybckgi60w.md":"0af2e5a6","yuque_start.md":"76db2088","yuque_ubcut43kgf97fag6.md":"21fb93a3","yuque_cq6p8hxizn1ogwgm.md":"103c2635","yuque_vy55q9xwlqlsfrvk.md":"fcb52f55","yuque_gvnxobqogetukays.md":"39b4a562","yuque_xe160pqsumi6bqnz.md":"e690f2aa","yuque_yuque-example.md":"adb9d329","yuque_yuque-markdown.md":"fe514f5f","yuque_zuzvbv2lqhvllgit.md":"7d7fbf58","feishu_vulcdslgxotcb1xli1bcwwdpnva.md":"0e963e8f","notion_qa.md":"d5f08f51","yuque-pwd_bry3d3lwe206xuor.md":"23f2a91d","notion_vy55q9xwlqlsfrvk.md":"75dadc1f","yuque-pwd_ubcut43kgf97fag6.md":"9f4f8b6a","notion_raqyleng501h23p1.md":"d3d3fb74","notion_start.md":"477eebce","notion_write-platform.md":"eae7bb35","notion_xe160pqsumi6bqnz.md":"aca40c37","notion_ubcut43kgf97fag6.md":"8c7a6779","yuque-pwd_gvnxobqogetukays.md":"5f9ac283","yuque-pwd_notion-markdown.md":"2daf9496","notion_yuque-markdown.md":"21593329","notion_zuzvbv2lqhvllgit.md":"4dd88278","yuque-pwd_notion-example.md":"35ae44bf","yuque-pwd_cq6p8hxizn1ogwgm.md":"de11db1f","yuque-pwd_raqyleng501h23p1.md":"0efd6107","yuque-pwd_introduce.md":"d0f2b654","yuque-pwd_la9toqncox96kfp8.md":"624859e5","yuque_fe8ywmt999gon12w.md":"576a3e18","notion_yuque-example.md":"d704f8a8","yuque-pwd_te7ash7ybckgi60w.md":"0a594655","yuque-pwd_vy55q9xwlqlsfrvk.md":"4ddba99e","yuque-pwd_fe8ywmt999gon12w.md":"2ad1b814","yuque-pwd_start.md":"598967f9","yuque_introduce.md":"8201672c"}
