{"notion_xe160pqsumi6bqnz.md":"Ka9QKz7l","notion_yuque-example.md":"u8JIAhKF","wolai_123.md":"qHV29r4w","yuque-pwd_bry3d3lwe206xuor.md":"Y09zMor_","notion_ubcut43kgf97fag6.md":"V3aKaYGS","notion_write-platform.md":"Wl9M6ITR","yuque-pwd_yuque-example.md":"WRrizuPm","flowus_flowus-test_7e7d1764-f879-4fd3-8d46-593c96994656.md":"y2ACuDDf","notion_flowus-markdown.md":"5_qOEd73","flowus_flowus-example.md":"QnaVYMDl","notion_gvnxobqogetukays.md":"0rsoQ2_u","flowus_flowus-test_2aeb1710-7a8f-46db-883c-a3da0d0dc7ea.md":"NuSTcxKw","notion_local-test.md":"vrwluYoh","notion_notion-markdown.md":"WARSHvIk","notion_la9toqncox96kfp8.md":"sF9yj_cA","notion_qa.md":"zNhJnVhc","index.md":"iORaV2ve","notion_introduce.md":"FvA4h54X","notion_flowus-example.md":"guY9c1x-","flowus_flowus-test.md":"F8xTHjS5","notion_blogpal.md":"n31HB9O7","notion_yuque-markdown.md":"RKMaYzGQ","notion_start.md":"v5zi-W3V","yuque-pwd_introduce.md":"-V0BK-AH","wolai_测试.md":"YBY7pjyB","feishu-wiki_docs_首页_首页下的文档_二级文档_三级文档_四级文档.md":"dDBQ5lxm","yuque-pwd_notion-example.md":"SBtu5Xf3","notion_bry3d3lwe206xuor.md":"DKD4I0Zw","yuque-pwd_start.md":"2Rony--T","wolai_测试12313123123.md":"0hk1HpO1","yuque-pwd_zuzvbv2lqhvllgit.md":"5M1lCnhu","yuque-pwd_notion-markdown.md":"fT_UjpDQ","yuque_cq6p8hxizn1ogwgm.md":"l0sFxqJx","yuque-pwd_te7ash7ybckgi60w.md":"NGs367-t","yuque-pwd_yuque-markdown.md":"qT0CWqd8","yuque-pwd_vy55q9xwlqlsfrvk.md":"WoAkRtvM","yuque_fe8ywmt999gon12w.md":"jl-HSbmJ","yuque_te7ash7ybckgi60w.md":"Jq-DIbvP","yuque-pwd_gvnxobqogetukays.md":"Pex3xyyw","feishu_一级子文件夹_iyyzdn2azoiwosxihracjp18ntb.md":"ogCZ-wvo","feishu_vulcdslgxotcb1xli1bcwwdpnva.md":"lT4zcafT","notion_raqyleng501h23p1.md":"miW9Vo5l","notion_config-catalog.md":"zpkK-3Zk","yuque_la9toqncox96kfp8.md":"udQ2EjBW","flowus_5556a4e0-3eaa-4940-9add-426a3e07b011.md":"DBiC-HS-","yuque_xe160pqsumi6bqnz.md":"0Ev_MLGC","yuque-pwd_fe8ywmt999gon12w.md":"oUWGDsDo","yuque_yuque-example.md":"OwF26Z8B","yuque_introduce.md":"vnI-u9_h","notion_deploy-platform.md":"6xSET2q9","notion_zuzvbv2lqhvllgit.md":"LJ6q21ON","yuque-pwd_raqyleng501h23p1.md":"4-YzrJbr","yuque_start.md":"5b86_h_s","feishu_一级子文件夹_二级文件夹_fpdsdgyc4ofs56xteghcnx2invf.md":"2tSJJt7F","yuque-pwd_ubcut43kgf97fag6.md":"s27anwZn","yuque_ubcut43kgf97fag6.md":"82KQEkiU","notion_feishu-example.md":"PfCF4Ufp","notion_vy55q9xwlqlsfrvk.md":"ECFPAYbM","notion_image-platform.md":"31yZ5-Uk","yuque_notion-markdown.md":"NVIhhwjG","flowus_flowus-example-2.md":"dd8LZlg8","yuque_zuzvbv2lqhvllgit.md":"vj7-tv_2","notion_fe8ywmt999gon12w.md":"YMGCR-5c","yuque_yuque-markdown.md":"EeTS9y9D","yuque_raqyleng501h23p1.md":"UfM8ziH7","notion_notion-example.md":"rpTmroOS","yuque-pwd_xe160pqsumi6bqnz.md":"VDAauGMY","yuque_gvnxobqogetukays.md":"hwz_mcMc","yuque_notion-example.md":"Xpo0j3ZY","notion_cq6p8hxizn1ogwgm.md":"0cEOvPmt","yuque_bry3d3lwe206xuor.md":"TP7rrO2P","yuque-pwd_cq6p8hxizn1ogwgm.md":"dOGRtTcZ","yuque-pwd_la9toqncox96kfp8.md":"u_p-US1M","yuque_vy55q9xwlqlsfrvk.md":"Dz-eZTpB","feishu-wiki_docs_测试.md":"ARpQ-31V"}
